adso/__init__.py
adso/common.py
adso/data/__init__.py
adso/data/common.py
adso/data/dataset.py
adso/data/newsgroups.py
adso/data/test.py
adso/topicmodel/__init__.py
adso/topicmodel/common.py
adso/topicmodel/lda.py
adso/topicmodel/nmf.py
adso/transform/__init__.py
adso/transform/common.py
adso/transform/filter.py
adso/transform/tokenizer.py
adso/transform/vectorizer.py
adso-0.0.1.post2.dist-info/LICENSE
adso-0.0.1.post2.dist-info/WHEEL
adso-0.0.1.post2.dist-info/METADATA
adso-0.0.1.post2.dist-info/RECORD
